rafuzzpandas/LICENSE.txt
rafuzzpandas/README.md
rafuzzpandas/__init__.py
rafuzzpandas/rafuzzpandas.pyx
rafuzzpandas/rafuzzpandas_compile.py
rafuzzpandas/requirements.txt
rafuzzpandas/thirdparty.json
rafuzzpandas-0.10.dist-info/LICENSE.rst
rafuzzpandas-0.10.dist-info/METADATA
rafuzzpandas-0.10.dist-info/WHEEL
rafuzzpandas-0.10.dist-info/top_level.txt
rafuzzpandas-0.10.dist-info/RECORD
