Metadata-Version: 2.1
Name: rafuzzpandas
Version: 0.10
Summary: Merges hard-to-merge data using rapidfuzz, cython, pandas and numpy
Home-page: https://github.com/hansalemaos/rafuzzpandas
Author: Johannes Fischer
Author-email: aulasparticularesdealemaosp@gmail.com
License: MIT
Keywords: data,fuzzy,merging,rapidfuzz,cython,pandas,numpy
Classifier: Development Status :: 4 - Beta
Classifier: Programming Language :: Python :: 3 :: Only
Classifier: Programming Language :: Python :: 3.10
Classifier: Topic :: Software Development :: Libraries :: Python Modules
Classifier: Topic :: Utilities
License-File: LICENSE.rst
Requires-Dist: Cython
Requires-Dist: normaltext
Requires-Dist: numpy
Requires-Dist: pandas
Requires-Dist: rapidfuzz
Requires-Dist: setuptools
